simple_automated_testing/__init__.py
simple_automated_testing/adapters/api/client.py
simple_automated_testing/adapters/api/interface.py
simple_automated_testing/adapters/bigquery/client.py
simple_automated_testing/adapters/bigquery/interface.py
simple_automated_testing/cli/app.py
simple_automated_testing/cli/errors.py
simple_automated_testing/cli/init_cmd.py
simple_automated_testing/cli/list_cmd.py
simple_automated_testing/cli/run.py
simple_automated_testing/config/discovery.py
simple_automated_testing/config/identity.py
simple_automated_testing/config/loader.py
simple_automated_testing/config/validation.py
simple_automated_testing/contracts/models.py
simple_automated_testing/contracts/transport.py
simple_automated_testing/core/executor.py
simple_automated_testing/core/pipeline.py
simple_automated_testing/core/pipeline_runner.py
simple_automated_testing/core/polling.py
simple_automated_testing/core/retry.py
simple_automated_testing/core/steps.py
simple_automated_testing/reporting/human.py
simple_automated_testing/reporting/junit.py
simple_automated_testing/sdk/builders.py
simple_automated_testing/utils/report_paths.py
simple_automated_testing/utils/time.py
simple_automated_testing/validators/api/assertions.py
simple_automated_testing/validators/api/interface.py
simple_automated_testing/validators/api/openapi.py
simple_automated_testing/validators/bigquery/data_rules.py
simple_automated_testing/validators/bigquery/interface.py
simple_automated_testing/validators/bigquery/schema.py
simple_automated_testing-0.1.0.dist-info/METADATA
simple_automated_testing-0.1.0.dist-info/WHEEL
simple_automated_testing-0.1.0.dist-info/entry_points.txt
simple_automated_testing-0.1.0.dist-info/top_level.txt
simple_automated_testing-0.1.0.dist-info/RECORD
