Metadata-Version: 2.4
Name: simple-automated-testing
Version: 0.1.0
Summary: Simple automated testing framework and CLI
Author-email: Simple Automated Testing <dev@example.com>
License: MIT
Keywords: testing,bigquery,cli
Classifier: Programming Language :: Python :: 3
Classifier: Programming Language :: Python :: 3.11
Classifier: License :: OSI Approved :: MIT License
Classifier: Operating System :: OS Independent
Requires-Python: >=3.11
Requires-Dist: typer>=0.12.0
Requires-Dist: PyYAML>=6.0.1
Requires-Dist: httpx>=0.27.0
Requires-Dist: google-cloud-bigquery>=3.25.0
Requires-Dist: openapi-spec-validator>=0.7.1
Requires-Dist: openapi-schema-validator>=0.6.0
Requires-Dist: jsonschema>=4.22.0
Provides-Extra: dev
Requires-Dist: pytest>=8.0.0; extra == "dev"
